IHEPDIRAC/__init__.py
IHEPDIRAC/Core/__init__.py
IHEPDIRAC/Core/Utilities/DErrno.py
IHEPDIRAC/Core/Utilities/__init__.py
IHEPDIRAC/DataManagementSystem/__init__.py
IHEPDIRAC/DataManagementSystem/scripts/__init__.py
IHEPDIRAC/DataManagementSystem/scripts/ihepdirac_dms_add_dir.py
IHEPDIRAC/DataManagementSystem/scripts/ihepdirac_dms_check_replicas.py
IHEPDIRAC/DataManagementSystem/scripts/ihepdirac_dms_register_EOS_files.py
IHEPDIRAC/DataManagementSystem/scripts/ihepdirac_dms_register_dir.py
IHEPDIRAC/DataManagementSystem/scripts/ihepdirac_dms_register_files.py
IHEPDIRAC/ResourceStatusSystem/__init__.py
IHEPDIRAC/ResourceStatusSystem/Agent/CacheFeederIHEPAgent.py
IHEPDIRAC/ResourceStatusSystem/Agent/SAMTestAgent.py
IHEPDIRAC/ResourceStatusSystem/Agent/__init__.py
IHEPDIRAC/ResourceStatusSystem/Client/ResourceManagementIHEPClient.py
IHEPDIRAC/ResourceStatusSystem/Client/__init__.py
IHEPDIRAC/ResourceStatusSystem/Command/HostCommand.py
IHEPDIRAC/ResourceStatusSystem/Command/JobIHEPCommand.py
IHEPDIRAC/ResourceStatusSystem/Command/SAMIHEPCommand.py
IHEPDIRAC/ResourceStatusSystem/Command/StorageIHEPCommand.py
IHEPDIRAC/ResourceStatusSystem/Command/WorkNodeIHEPCommand.py
IHEPDIRAC/ResourceStatusSystem/Command/__init__.py
IHEPDIRAC/ResourceStatusSystem/DB/ResourceManagementIHEPDB.py
IHEPDIRAC/ResourceStatusSystem/DB/__init__.py
IHEPDIRAC/ResourceStatusSystem/Policy/Configurations.py
IHEPDIRAC/ResourceStatusSystem/Policy/SiteSAMPolicy.py
IHEPDIRAC/ResourceStatusSystem/Policy/__init__.py
IHEPDIRAC/ResourceStatusSystem/PolicySystem/__init__.py
IHEPDIRAC/ResourceStatusSystem/PolicySystem/Actions/EmailAction.py
IHEPDIRAC/ResourceStatusSystem/PolicySystem/Actions/__init__.py
IHEPDIRAC/ResourceStatusSystem/SAM/StatusEvaluator.py
IHEPDIRAC/ResourceStatusSystem/SAM/TestExecutor.py
IHEPDIRAC/ResourceStatusSystem/SAM/__init__.py
IHEPDIRAC/ResourceStatusSystem/SAM/SAMTest/AccessTest.py
IHEPDIRAC/ResourceStatusSystem/SAM/SAMTest/BOSSTest.py
IHEPDIRAC-2.2.8.dist-info/LICENSE
IHEPDIRAC-2.2.8.dist-info/METADATA
IHEPDIRAC-2.2.8.dist-info/WHEEL
IHEPDIRAC-2.2.8.dist-info/entry_points.txt
IHEPDIRAC-2.2.8.dist-info/top_level.txt
IHEPDIRAC-2.2.8.dist-info/RECORD
