Metadata-Version: 2.1
Name: IHEPDIRAC
Version: 2.2.8
Summary: IHEPDIRAC is the IHEP extension of DIRAC
Home-page: https://code.ihep.ac.cn/Grid/IHEPDIRAC
Classifier: Programming Language :: Python :: 3
Classifier: License :: OSI Approved :: MIT License
Classifier: Operating System :: OS Independent
Requires-Python: >=3.9
License-File: LICENSE
Requires-Dist: DIRAC
Provides-Extra: server
Requires-Dist: DIRAC[server]~=8.0.0; extra == "server"
Requires-Dist: WebAppDIRAC~=5.0.4; extra == "server"
Requires-Dist: DIRACWebAppResources~=1.0; extra == "server"
Requires-Dist: psutil; extra == "server"
Requires-Dist: stomp.py; extra == "server"
Requires-Dist: suds-jurko; extra == "server"
Provides-Extra: testing
Requires-Dist: mock; extra == "testing"
Requires-Dist: Pillow; extra == "testing"
Requires-Dist: pytest; extra == "testing"
